cyberfusion/FastRedirect/__init__.py
cyberfusion/FastRedirect/database.py
cyberfusion/FastRedirect/endpoints.py
cyberfusion/FastRedirect/middleware.py
cyberfusion/FastRedirect/server.py
cyberfusion/FastRedirect/settings.py
cyberfusion/FastRedirect/utilities.py
cyberfusion/FastRedirect/exceptions/__init__.py
cyberfusion/FastRedirect/exceptions/database.py
cyberfusion/FastRedirect/exceptions/http_host_header.py
python3_cyberfusion_fast_redirect-1.1.dist-info/METADATA
python3_cyberfusion_fast_redirect-1.1.dist-info/WHEEL
python3_cyberfusion_fast_redirect-1.1.dist-info/entry_points.txt
python3_cyberfusion_fast_redirect-1.1.dist-info/top_level.txt
python3_cyberfusion_fast_redirect-1.1.dist-info/RECORD
