Metadata-Version: 2.4
Name: python3-cyberfusion-fast-redirect
Version: 1.1
Summary: fast-redirect redirects domains.
Author-email: Cyberfusion <support@cyberfusion.io>
Project-URL: Source, https://github.com/CyberfusionIO/python3-cyberfusion-fast-redirect
Requires-Dist: starlette==0.46.1
Requires-Dist: uvicorn==0.32.0
Requires-Dist: validators==0.20.0
